[
 {
  "shisya": "40",
  "danchi": "248",
  "shikibetu": "0",
  "danchiNm": "かわさきテクノピア堀川町ハイツ",
  "commute_min": 42
 },
 {
  "shisya": "40",
  "danchi": "402",
  "shikibetu": "0",
  "danchiNm": "アーベインビオ川崎",
  "commute_min": 42
 },
 {
  "shisya": "40",
  "danchi": "219",
  "shikibetu": "0",
  "danchiNm": "サンスクエア川崎",
  "commute_min": 44
 },
 {
  "shisya": "40",
  "danchi": "183",
  "shikibetu": "0",
  "danchiNm": "川崎日進",
  "commute_min": 47
 },
 {
  "shisya": "40",
  "danchi": "151",
  "shikibetu": "0",
  "danchiNm": "鶴見町",
  "commute_min": 48
 },
 {
  "shisya": "40",
  "danchi": "266",
  "shikibetu": "0",
  "danchiNm": "小杉御殿",
  "commute_min": 49
 },
 {
  "shisya": "40",
  "danchi": "404",
  "shikibetu": "0",
  "danchiNm": "リーデンスフォート横浜",
  "commute_min": 50
 },
 {
  "shisya": "40",
  "danchi": "412",
  "shikibetu": "0",
  "danchiNm": "コンフォール川崎富士見",
  "commute_min": 51
 },
 {
  "shisya": "40",
  "danchi": "177",
  "shikibetu": "0",
  "danchiNm": "鶴見町第二",
  "commute_min": 51
 },
 {
  "shisya": "40",
  "danchi": "340",
  "shikibetu": "0",
  "danchiNm": "ステラ月見ヶ丘",
  "commute_min": 52
 },
 {
  "shisya": "40",
  "danchi": "260",
  "shikibetu": "0",
  "danchiNm": "川崎旭町ハイツ",
  "commute_min": 52
 },
 {
  "shisya": "40",
  "danchi": "420",
  "shikibetu": "0",
  "danchiNm": "ミラリオ大師河原",
  "commute_min": 53
 },
 {
  "shisya": "40",
  "danchi": "401",
  "shikibetu": "0",
  "danchiNm": "オルトヨコハマ　ビュータワー",
  "commute_min": 54
 },
 {
  "shisya": "40",
  "danchi": "269",
  "shikibetu": "0",
  "danchiNm": "港北ニュータウン　サントゥール中川",
  "commute_min": 55
 }
]
